algotradepy/__init__.py
algotradepy/_version.py
algotradepy/contracts.py
algotradepy/docstring_utils.py
algotradepy/ib_utils.py
algotradepy/order_conditions.py
algotradepy/orders.py
algotradepy/path_utils.py
algotradepy/sim_utils.py
algotradepy/subscribable.py
algotradepy/tick.py
algotradepy/time_utils.py
algotradepy/trade.py
algotradepy/utils.py
algotradepy/brokers/__init__.py
algotradepy/brokers/base.py
algotradepy/brokers/ib_broker.py
algotradepy/brokers/sim_broker.py
algotradepy/connectors/__init__.py
algotradepy/connectors/ib_connector.py
algotradepy/connectors/iex_connector.py
algotradepy/connectors/polygon_connector.py
algotradepy/historical/__init__.py
algotradepy/historical/hist_utils.py
algotradepy/historical/loaders.py
algotradepy/historical/transformers.py
algotradepy/historical/providers/__init__.py
algotradepy/historical/providers/base.py
algotradepy/historical/providers/iex_provider.py
algotradepy/historical/providers/polygon_provider.py
algotradepy/historical/providers/yahoo_provider.py
algotradepy/streamers/__init__.py
algotradepy/streamers/base.py
algotradepy/streamers/ib_streamer.py
algotradepy/streamers/polygon_streamer.py
algotradepy/streamers/sim_streamer.py
algotradepy-0.2.4.data/scripts/aggregator.py
algotradepy-0.2.4.data/scripts/downloader.py
tests/__init__.py
tests/conftest.py
tests/test_contracts.py
tests/test_historical.py
tests/test_sim_utils.py
tests/brokers/__init__.py
tests/brokers/test_ib_broker.py
tests/brokers/test_sim_broker.py
tests/connectors/__init__.py
tests/connectors/test_ib_connector.py
tests/connectors/test_polygon_connector.py
tests/connectors/test_utils.py
tests/streamers/__init__.py
tests/streamers/test_ib_streamer.py
tests/streamers/test_polygon_streamer.py
tests/streamers/test_sim_streamer.py
algotradepy-0.2.4.dist-info/LICENSE.txt
algotradepy-0.2.4.dist-info/METADATA
algotradepy-0.2.4.dist-info/WHEEL
algotradepy-0.2.4.dist-info/top_level.txt
algotradepy-0.2.4.dist-info/RECORD
