Metadata-Version: 2.1
Name: algotradepy
Version: 0.2.4
Summary: Python Auto-Trading Framework
Home-page: https://github.com/petioptrv/automated-trading
Author: Petio Petrov
Author-email: petioptrv@icloud.com
License: MIT License
Requires-Dist: numpy (<2,>=1)
Requires-Dist: pandas (<2,>=1)
Requires-Dist: yfinance (<1)
Requires-Dist: pandas-datareader (<1,>=0.4.0)
Requires-Dist: requests (<3,>=2)
Requires-Dist: pandas-market-calendars (<2,>=1)
Provides-Extra: dev
Requires-Dist: pytest ; extra == 'dev'
Requires-Dist: pylint ; extra == 'dev'
Requires-Dist: pre-commit ; extra == 'dev'
Requires-Dist: versioneer ; extra == 'dev'
Requires-Dist: black ; extra == 'dev'
Requires-Dist: flake8 ; extra == 'dev'
Requires-Dist: flake8-black ; extra == 'dev'
Requires-Dist: twine ; extra == 'dev'
Requires-Dist: sphinx ; extra == 'dev'
Requires-Dist: sphinx-rtd-theme ; extra == 'dev'
Provides-Extra: ibapi
Requires-Dist: ib-insync (<1,>=0.9) ; extra == 'ibapi'
Requires-Dist: ibapi ; extra == 'ibapi'
Provides-Extra: polygon
Requires-Dist: websocket-client (==0.57.0) ; extra == 'polygon'
